typeright/__init__.py
typeright/__main__.py
typeright/annotations/__init__.py
typeright/annotations/infer.py
typeright/annotations/main.py
typeright/annotations/parse.py
typeright/annotations/tests/__init__.py
typeright/annotations/tests/dundermain_test.py
typeright/annotations/tests/infer_test.py
typeright/annotations/tests/main_test.py
typeright/annotations/tests/parse_test.py
typeright/annotations/tests/types_test.py
typeright/annotations/types.py
typeright/docs/__init__.py
typeright/docs/formats.py
typeright/docs/parsers/__init__.py
typeright/docs/parsers/other.py
typeright/docs/parsers/rest.py
typeright/fixes/__init__.py
typeright/fixes/base.py
typeright/fixes/fix_annotate_any.py
typeright/fixes/fix_annotate_command.py
typeright/fixes/fix_annotate_docs.py
typeright/fixes/fix_annotate_json.py
typeright/fixes/fixer_utils.py
typeright/fixes/tests/__init__.py
typeright/fixes/tests/base_py2.py
typeright/fixes/tests/base_py3.py
typeright/fixes/tests/test_annotate_any_py2.py
typeright/fixes/tests/test_annotate_any_py3.py
typeright/fixes/tests/test_annotate_command_py2.py
typeright/fixes/tests/test_annotate_command_py3.py
typeright/fixes/tests/test_annotate_json_py2.py
typeright/fixes/tests/test_annotate_json_py3.py
typeright/fixes/tests/test_util.py
typeright-0.1.0.dist-info/LICENSE
typeright-0.1.0.dist-info/METADATA
typeright-0.1.0.dist-info/WHEEL
typeright-0.1.0.dist-info/entry_points.txt
typeright-0.1.0.dist-info/RECORD
