Metadata-Version: 2.1
Name: typeright
Version: 0.1.0
Summary: Add type annotations to your source code
Home-page: https://github.com/chadrik/typeright
License: Apache-2.0
Keywords: pep484,typing,annotations,mypy
Author: Chad Dombrova
Author-email: chadrik@gmail.com
Requires-Python: >=2.7, !=3.0.*, !=3.1.*, !=3.2.*, !=3.3.*, !=3.4.*, !=3.5.*
Classifier: Development Status :: 3 - Alpha
Classifier: Environment :: Console
Classifier: Intended Audience :: Developers
Classifier: License :: OSI Approved :: Apache Software License
Classifier: Operating System :: POSIX
Classifier: Programming Language :: Python :: 2
Classifier: Programming Language :: Python :: 2.7
Classifier: Programming Language :: Python :: 3
Classifier: Programming Language :: Python :: 3.6
Classifier: Programming Language :: Python :: 3.7
Classifier: Programming Language :: Python :: 3.8
Classifier: Programming Language :: Python :: 3.9
Classifier: Programming Language :: Python :: 3.10
Classifier: Programming Language :: Python :: 3.11
Classifier: Programming Language :: Python :: 2
Classifier: Programming Language :: Python :: 2.7
Classifier: Programming Language :: Python :: 3
Classifier: Programming Language :: Python :: 3.6
Classifier: Programming Language :: Python :: 3.7
Classifier: Programming Language :: Python :: 3.8
Classifier: Topic :: Software Development
Provides-Extra: tests
Requires-Dist: coverage ; extra == "tests"
Requires-Dist: docutils
Requires-Dist: kids.cache
Requires-Dist: mypy_extensions (>=0.3.0) ; extra == "tests"
Requires-Dist: pytest (>=6.1,<7.0) ; extra == "tests"
Requires-Dist: pytest-mock ; extra == "tests"
Requires-Dist: six
Requires-Dist: typing (>=3.7.0,<3.8.0) ; python_version < "3.7"
Requires-Dist: typing-extensions (>=3.7.4.3) ; extra == "tests"
Project-URL: Repository, https://github.com/chadrik/typeright
